titta/TalkToProLab.py
titta/TalkToProLab_dummy.py
titta/Titta.py
titta/Tobii.py
titta/Tobii_dummy.py
titta/__init__.py
titta/helpers_tobii.py
titta/version.py
titta-2.2.1.dist-info/LICENSE.md
titta-2.2.1.dist-info/METADATA
titta-2.2.1.dist-info/WHEEL
titta-2.2.1.dist-info/top_level.txt
titta-2.2.1.dist-info/RECORD
