Metadata-Version: 2.1
Name: titta
Version: 2.2.1
Summary: Titta is a toolbox for using eye trackers from Tobii with Python, specifically offering integration with PsychoPy.
Home-page: https://github.com/marcus-nystrom/Titta
Author: Marcus Nystrom
Author-email: marcus.nystrom@humlab.lu.se
License: Creative Commons Attribution 4.0 (CC BY 4.0)
Project-URL: Source Code, https://github.com/marcus-nystrom/Titta
Classifier: Development Status :: 5 - Production/Stable
Classifier: Intended Audience :: Science/Research
Classifier: Topic :: Scientific/Engineering
Classifier: Topic :: Software Development :: Libraries
Classifier: Environment :: MacOS X
Classifier: Environment :: Win32 (MS Windows)
Classifier: Environment :: X11 Applications
Classifier: Operating System :: Microsoft :: Windows
Classifier: Operating System :: MacOS :: MacOS X
Classifier: Operating System :: POSIX :: Linux
Classifier: Programming Language :: Python :: 3
Requires-Python: >=3.8
License-File: LICENSE.md
Requires-Dist: numpy
Requires-Dist: pandas
Requires-Dist: h5py
Requires-Dist: TittaPy >=2
Requires-Dist: websocket-client
